Ejercicio4/1_3/1_3.v
module tabla_3(input wire A,B,C,D, output wire Y);

  assign Y = (~A & ~B & ~C & ~D) | (~A & ~B & C & D) | (~A & B & ~C & D) | (~A & B & C & ~D) | (A & ~B & ~C & D) | (A & ~B & C & ~D) | (A & B & ~C & ~D) | (A & B & C & D);
              
endmodule

Ejercicio4/1_3/1_3_tb.v
module testbench();

reg A, B, C, D;
wire Y;

tabla_3 U2(A, B, C, D, Y);

initial begin
  #30
  $display("A B C D | Y");
  $display("--------|--");
  $monitor("%b %b %b %b | %b", A, B, C, D, Y);
     A = 0; B = 0; C = 0; D = 0;
  #1 A = 0; B = 0; C = 0; D = 1;
  #1 A = 0; B = 0; C = 1; D = 0;
  #1 A = 0; B = 0; C = 1; D = 1;
  #1 A = 0; B = 1; C = 0; D = 0;
  #1 A = 0; B = 1; C = 0; D = 1;
  #1 A = 0; B = 1; C = 1; D = 0;
  #1 A = 0; B = 1; C = 1; D = 1;
  #1 A = 1; B = 0; C = 0; D = 0;
  #1 A = 1; B = 0; C = 0; D = 1;
  #1 A = 1; B = 0; C = 1; D = 0;
  #1 A = 1; B = 0; C = 1; D = 1;
  #1 A = 1; B = 1; C = 0; D = 0;
  #1 A = 1; B = 1; C = 0; D = 1;
  #1 A = 1; B = 1; C = 1; D = 0;
  #1 A = 1; B = 1; C = 1; D = 1;

end

initial
  #50 $finish;

initial begin
  $dumpfile("1_3_tb.vcd");
  $dumpvars(0, testbench);
end

endmodule

Ejercicio4/1_3/1_3_tb.vcd
$date
	Sun Aug 09 20:53:28 2020
$end
$version
	Icarus Verilog
$end
$timescale
	1ps
$end
$scope module testbench $end
$var wire 1 ! Y $end
$var reg 1 " A $end
$var reg 1 # B $end
$var reg 1 $ C $end
$var reg 1 % D $end
$scope module U2 $end
$var wire 1 " A $end
$var wire 1 # B $end
$var wire 1 $ C $end
$var wire 1 % D $end
$var wire 1 ! Y $end
$upscope $end
$upscope $end
$enddefinitions $end
#0
$dumpvars
x%
x$
x#
x"
x!
$end
#30
1!
0%
0$
0#
0"
#31
0!
1%
#32
0%
1$
#33
1!
1%
#34
0!
0%
0$
1#
#35
1!
1%
#36
0%
1$
#37
0!
1%
#38
0%
0$
0#
1"
#39
1!
1%
#40
0%
1$
#41
0!
1%
#42
1!
0%
0$
1#
#43
0!
1%
#44
0%
1$
#45
1!
1%
